simplesapi/__init__.py
simplesapi/app.py
simplesapi/auto_routing.py
simplesapi-0.1.0.dist-info/METADATA
simplesapi-0.1.0.dist-info/WHEEL
simplesapi-0.1.0.dist-info/RECORD
