Metadata-Version: 2.1
Name: SimplesAPI
Version: 0.1.0
Summary: SimplesAPI is intended to be the easiest API to implementation in Python
Author: Anderson Magalhaes
Author-email: andersonmagalhaes.dev@gmail.com
Requires-Python: >=3.12,<4.0
Classifier: Programming Language :: Python :: 3
Classifier: Programming Language :: Python :: 3.12
Requires-Dist: fastapi (>=0.111.0,<0.112.0)
